SareanArsenal/__init__.py
SareanArsenal/notifications/__init__.py
SareanArsenal/notifications/push.py
SareanArsenal/risingStones/__init__.py
SareanArsenal/risingStones/rs_binding_character.py
SareanArsenal/risingStones/rs_comment.py
SareanArsenal/risingStones/rs_get_current_signReward.py
SareanArsenal/risingStones/rs_get_current_user_info.py
SareanArsenal/risingStones/rs_get_uid_user_info.py
SareanArsenal/risingStones/rs_like.py
SareanArsenal/risingStones/rs_signIn.py
SareanArsenal/sdoLogin/__init__.py
SareanArsenal/sdoLogin/daoyu_utility.py
SareanArsenal/sdoLogin/sdo_web_qrcode_login.py
SareanArsenal/sqMall/__init__.py
SareanArsenal/sqMall/daoyuBuildinMallBalance.py
SareanArsenal/sqMall/daoyuBuildinMallSign.py
SareanArsenal/sqMall/sqMall_signin.py
SareanArsenal-1.0.3.dist-info/METADATA
SareanArsenal-1.0.3.dist-info/WHEEL
SareanArsenal-1.0.3.dist-info/top_level.txt
SareanArsenal-1.0.3.dist-info/RECORD
