Metadata-Version: 2.1
Name: SareanArsenal
Version: 1.0.3
Summary: A FF14CN Tool kit
Author: FF14.CN ORG.
Author-email: hi@ff14.cn
Requires-Dist: requests
Requires-Dist: kuai-log
Requires-Dist: pyzbar
Requires-Dist: pillow
